brother_ql/__init__.py
brother_ql/brother_ql_analyse.py
brother_ql/brother_ql_create.py
brother_ql/brother_ql_debug.py
brother_ql/brother_ql_info.py
brother_ql/brother_ql_print.py
brother_ql/cli.py
brother_ql/conversion.py
brother_ql/devicedependent.py
brother_ql/exceptions.py
brother_ql/helpers.py
brother_ql/image_trafos.py
brother_ql/labels.py
brother_ql/models.py
brother_ql/output_helpers.py
brother_ql/raster.py
brother_ql/reader.py
brother_ql/backends/__init__.py
brother_ql/backends/generic.py
brother_ql/backends/helpers.py
brother_ql/backends/linux_kernel.py
brother_ql/backends/network.py
brother_ql/backends/pyusb.py
brother_ql-0.9.4.dist-info/METADATA
brother_ql-0.9.4.dist-info/RECORD
brother_ql-0.9.4.dist-info/WHEEL
brother_ql-0.9.4.dist-info/entry_points.txt
brother_ql-0.9.4.dist-info/top_level.txt
brother_ql-0.9.4.dist-info/zip-safe
